MANIFEST.in
readme.md
setup.py
ddsf/__init__.py
ddsf/ddsf.py
ddsf/resource.py
ddsf.egg-info/PKG-INFO
ddsf.egg-info/SOURCES.txt
ddsf.egg-info/dependency_links.txt
ddsf.egg-info/requires.txt
ddsf.egg-info/top_level.txt