Metadata-Version: 2.1
Name: ddsf
Version: 0.0.42
Summary: access dsf
Home-page: https://gitlab.hrz.tu-chemnitz.de/slm/python-ddsf
Author: Lukas Jurk
Author-email: lukas.jurk@tu-dresden.de
License: UNKNOWN
Platform: UNKNOWN
